{
  "auditEventIds": ["ADM-027", "ADM-049"],
  "actionButtons": [
    {
      "buttonName": {
        "eng": "Approve",
	"ara": "Approve_ara",
	"fra": "Approve_fra"
      },
      "actionURL": "",
      "redirectURL": "",
      "showIn": "Ellipsis",
      "validations": "",
      "callBackFunction": "approve"
    },
    {
      "buttonName": {
        "eng": "Reject",
	"ara": "Reject_ara",
	"fra": "Reject_fra"
      },
      "actionURL": "",
      "redirectURL": "",
      "showIn": "Ellipsis",
      "validations": "",
      "callBackFunction": "reject"
    },
    {
      "buttonName": {
        "eng": "Edit",
	"ara": "Edit_ara",
	"fra": "Edit_fra"
      },
      "actionURL": "",
      "redirectURL": "/pmp/resources/devicedetails/single-view/$id",
      "showIn": "Ellipsis",
      "validations": "",
      "callBackFunction": "partnerEdit"
    },
    {
      "buttonName": {
        "eng": "SBI Details",
	"ara": "SBI Details_ara",
	"fra": "SBI Details_fra"
      },
      "actionURL": "",
      "redirectURL": "/pmp/resources/devicedetails/sbidetails/view/$id",
      "showIn": "Ellipsis",
      "validations": "",
      "callBackFunction": "deviceDetail"
    },
    {
      "buttonName": {
        "eng": "Create Device",
	"ara": "Create Device_ara",
	"fra": "Create Device_fra"
      },
      "imagePath": "assets/images/add-icon.png",
      "actionListType": "redirect",
      "actionURL": "",
      "redirectURL": "pmp/resources/devicedetails/create",
      "showIn": "Button",
      "validations": ""
    },
    {
      "buttonName": { "eng": "Filter", "ara": "Filter_ara", "fra": "Filter_fra" },
      "imagePath": "assets/images/filter.png",
      "actionListType": "action",
      "actionURL": { "case": "filter" },
      "redirectURL": "",
      "showIn": "Button",
      "validations": ""
    }
  ],
  "columnsToDisplay": [    
    {
      "name": "id",
      "label": { "eng": "ID","ara": "ID_ara","fra": "ID_fra"},
      "sortOrder": "",
      "showAsLink": "",
      "linkType": "",
      "LinkURL": "",
      "inputType": "",
      "ismandatory": "",
      "showInListView": "false",
      "showInSingleView": "false"
    },
    {
      "name": "deviceProviderId",
      "label": { "eng": "Partner Name","ara": "Partner Name_ara","fra": "Partner Name_fra"},
      "sortOrder": "",
      "showAsLink": "",
      "linkType": "",
      "LinkURL": "",
      "inputType": "dropdown",
      "ismandatory": "true",
      "showInListView": "true",
      "showInSingleView": "true"
    },
    {
      "name": "partnerOrganizationName",
      "label": { "eng": "Organization Name","ara": "Organization Name_ara","fra": "Organization Name_fra"},
      "sortOrder": "",
      "showAsLink": "",
      "linkType": "",
      "LinkURL": "",
      "inputType": "",
      "ismandatory": "",
      "showInListView": "true",
      "showInSingleView": "false"
    },
    {
      "name": "deviceTypeCode",
      "label": { "eng": "Device Type","ara": "Device Type_ara","fra": "Device Type_fra"},
      "sortOrder": "",
      "showAsLink": "",
      "linkType": "",
      "LinkURL": "",
      "inputType": "dropdown",
      "ismandatory": "true",
      "showInListView": "true",
      "showInSingleView": "true"
    },
    {
      "name": "deviceSubTypeCode",
      "label": { "eng": "Device Sub Type","ara": "Device Sub Type_ara","fra": "Device Sub Type_fra"},
      "sortOrder": "",
      "showAsLink": "",
      "linkType": "",
      "LinkURL": "",
      "inputType": "dropdown",
      "ismandatory": "true",
      "showInListView": "true",
      "showInSingleView": "true"
    },
    {
      "name": "make",
      "label": { "eng": "Make","ara": "Make_ara","fra": "Make_fra"},
      "sortOrder": "",
      "showAsLink": "",
      "linkType": "",
      "LinkURL": "",
      "inputType": "text",
      "ismandatory": "true",
      "showInListView": "true",
      "showInSingleView": "true"
    },
    {
      "name": "model",
      "label": { "eng": "Model","ara": "Model_ara","fra": "Model_fra"},
      "sortOrder": "",
      "showAsLink": "",
      "linkType": "",
      "LinkURL": "",
      "inputType": "text",
      "ismandatory": "true",
      "showInListView": "true",
      "showInSingleView": "true"
    },
    {
      "name": "isItForRegistrationDevice",
      "label": { "eng": "ForRegistrationDevice","ara": "ForRegistrationDevice_ara","fra": "ForRegistrationDevice_fra"},
      "sortOrder": "",
      "showAsLink": "",
      "linkType": "",
      "LinkURL": "",
      "inputType": "dropdown",
      "ismandatory": "true",
      "showInListView": "false",
      "showInSingleView": "false"
    },
    {
      "name": "isActive",
      "showInListView": "true",
      "label": { "eng": "Approved Status","ara": "Approved Status_ara","fra": "Approved Status_fra"},
      "sortOrder": "",
      "showAsLink": "",
      "linkType": "",
      "LinkURL": ""  
    }
  ],
  "paginator": {
    "totalEntries": null,
    "pageSize": "10",
    "pageSizeList": [10, 20, 30, 40, 50]
  },
  "filterColumns": [
  {
    "filtername": "deviceProviderId",
    "filterlabel": "Partner Name",
    "filterType": "equals",
    "fieldType": "input",
    "autocomplete": "false",
    "dropdown": "false",
    "datePicker": "false",
    "apiName": "",
    "fieldName": "deviceProviderId",
    "methodCallName": ""
  },
  {
    "filtername": "partnerOrganizationName",
    "filterlabel": "Organization Name",
    "filterType": "equals",
    "fieldType": "input",
    "autocomplete": "false",
    "dropdown": "false",
    "datePicker": "false",
    "apiName": "",
    "fieldName": "partnerOrganizationName",
    "methodCallName": ""
  },
  {
    "filtername": "deviceTypeCode",
    "filterlabel": "Device Type",
    "filterType": "equals",
    "fieldType": "input",
    "autocomplete": "false",
    "dropdown": "false",
    "datePicker": "false",
    "apiName": "",
    "fieldName": "deviceTypeCode",
    "methodCallName": ""
  },
  {
    "filtername": "deviceSubTypeCode",
    "filterlabel": "Device Sub Type",
    "filterType": "equals",
    "fieldType": "input",
    "autocomplete": "false",
    "dropdown": "false",
    "datePicker": "false",
    "apiName": "",
    "fieldName": "deviceSubTypeCode",
    "methodCallName": ""
  },
  {
    "filtername": "make",
    "filterlabel": "Make",
    "filterType": "equals",
    "fieldType": "input",
    "autocomplete": "false",
    "dropdown": "false",
    "datePicker": "false",
    "apiName": "",
    "fieldName": "make",
    "methodCallName": ""
  },
  {
    "filtername": "model",
    "filterlabel": "Model",
    "filterType": "equals",
    "fieldType": "input",
    "autocomplete": "false",
    "dropdown": "false",
    "datePicker": "false",
    "apiName": "",
    "fieldName": "model",
    "methodCallName": ""
  }
  ]
}
